Mathematics_Module/Maths.py
Mathematics_Module/__init__.py
Mathematics_Module-0.1.dist-info/LICENSE.txt
Mathematics_Module-0.1.dist-info/METADATA
Mathematics_Module-0.1.dist-info/WHEEL
Mathematics_Module-0.1.dist-info/top_level.txt
Mathematics_Module-0.1.dist-info/RECORD
