Metadata-Version: 2.1
Name: Mathematics-Module
Version: 0.1
Summary: Mathematics module
Home-page: UNKNOWN
Author: sid
Author-email: sid.garg@gmail.com
License: UNKNOWN
Platform: UNKNOWN
Classifier: Programming Language :: Python :: 3
Classifier: License :: OSI Approved :: MIT License
Classifier: Operating System :: OS Independent
